APB/apb_slave2.v
module apb_slave2(
input clk,
input reset,
input psel,
input penable,
input [7:0] paddr,
input [7:0] pwdata,
input pwrite,

output reg pready2,
output reg [7:0] prdata2
);

reg [7:0] mem[0:255];

integer i;
initial begin
        for(i=0;i<256;i=i+1)
                mem[i]=8'b0;
end
always @(posedge clk) begin
        if(reset) begin
                for(i=0;i<256;i=i+1)
                        mem[i]<=8'b0;
        end
        else if(psel && penable && pwrite && pready2)
                mem[paddr]<=pwdata;
end

always @(*) begin
    pready2 = 1'b0;
    prdata2 = 8'b0;

    if(psel && penable) begin
        pready2 = 1'b1;

        if(!pwrite)
            prdata2 = mem[paddr];
    end
end


endmodule

APB/apb_slave.v
module apb_slave1(
input clk,
input reset,
input psel,
input penable,
input [7:0] paddr,
input [7:0] pwdata,
input pwrite,

output reg pready1,
output reg [7:0] prdata1
);

reg [7:0] mem[0:255];

integer i;
initial begin
	for(i=0;i<256;i=i+1)
		mem[i]=8'b0;
end
always @(posedge clk) begin
	if(reset) begin
		for(i=0;i<256;i=i+1)
			mem[i]<=8'b0;
	end
	else if(psel && penable && pwrite && pready1)
		mem[paddr]<=pwdata;
end

always @(*) begin
    pready1 = 1'b0;
    prdata1 = 8'b0;

    if(psel && penable) begin
        pready1 = 1'b1;

        if(!pwrite)
            prdata1 = mem[paddr];
    end
end


endmodule

APB/apb_master.v
module apb_master(
input clk,
input reset,
input write,
input transfer,
input [7:0] addr,
input [7:0] data_in,

input pready,
input [7:0] prdata,


output reg psel,penable,pwrite,
output reg [7:0] paddr,
output reg [7:0] pwdata,
output reg [7:0] read_out
);

localparam IDLE =2'b00,SETUP=2'b01,ACCESS=2'b10;

reg [1:0] state,nextstate;

// STATE LOGIC
always @(posedge clk) begin
if(reset)  begin
state<=IDLE;
read_out<=8'b0;
end

else begin
state<=nextstate;
if(state==ACCESS && pready && !pwrite)
	read_out<=prdata;
end
end

//NEXTSTATE LOGIC
always @(*) begin
case(state)
IDLE: begin
if(transfer) 
nextstate=SETUP;
else
nextstate=IDLE;
end
SETUP: begin
nextstate=ACCESS;
end
ACCESS: begin
if(pready) begin
if(transfer)
nextstate=SETUP;
else
nextstate=IDLE;
end
else 
nextstate=ACCESS;
end
default:
	nextstate=IDLE;
endcase
end

//OUTPUT LOGIC
always @(*) begin
    psel    = 0;
    penable = 0;
    pwrite  = 0;
    paddr   = 0;
    pwdata  = 0;

    case(state)
        IDLE: begin
            psel = 0;
            penable = 0;
        end

        SETUP: begin
            psel = 1;
            penable = 0;
            pwrite = write;
            paddr = addr;
            pwdata = data_in;
        end

        ACCESS: begin
            psel = 1;
            penable = 1;
            pwrite = write;
            paddr = addr;
            pwdata = data_in;
        end
	default: begin
		psel=0;
		penable=0;
	end

    endcase
end
endmodule

APB/apb_tb.v
module apb_tb();
reg clk,reset,write,transfer;
reg [7:0] addr;
reg [7:0] data_in;
wire pready;
wire [7:0] prdata;
wire psel,penable,pwrite;
wire [7:0] paddr;
wire [7:0] pwdata;
wire [7:0] read_out;

wire psel0,psel1;
wire pready0,pready1;
wire [7:0] prdata0,prdata1;


apb_master dut(.clk(clk),.reset(reset),.write(write),.transfer(transfer),.addr(addr),.data_in(data_in),.pready(pready),.prdata(prdata),
               .psel(psel),.pwrite(pwrite),.penable(penable),.paddr(paddr),.pwdata(pwdata),.read_out(read_out));
apb_slave1 dut1(.clk(clk),.reset(reset),.psel(psel0),.penable(penable),.paddr(paddr),.pwdata(pwdata),.pwrite(pwrite),.pready1(pready0),.prdata1(prdata0));
apb_slave2 dut2 (.clk(clk),.reset(reset),.psel(psel1),.penable(penable),.paddr(paddr),.pwdata(pwdata),.pwrite(pwrite),.pready2(pready1),.prdata2(prdata1));
assign psel0 = psel && (paddr[7]==1'b0);   
assign psel1 = psel && (paddr[7]==1'b1);   
assign pready = psel0 ? pready0 : (psel1 ? pready1 : 1'b0);
assign prdata = psel0 ? prdata0 : (psel1 ? prdata1 : 8'b0);

initial begin
clk=0;
forever #10 clk=~clk;
end

initial begin
$dumpfile("apb.vcd");
$dumpvars(0,apb_tb);
  $monitor("time=%0t state=%0d psel=%b penable=%b pready=%b paddr=%h pwdata=%h",
            $time, dut.state, psel, penable, pready, paddr, pwdata);

//RESET COND
reset=1;
write=0;transfer=0;addr=0;data_in=0;
#20;

reset=0;
//WRITE TEST 
addr=8'hA5;
data_in=8'h77;
write=1;
transfer=1;
#40;
transfer=0;
#20;


// READ BACK TEST
addr=8'hA5;
write=0;
transfer=1;
#40;
transfer=0;
#20;

//WRITE TEST
addr=8'h43;
data_in=8'h21;
write=1;
transfer=1;
#40;
transfer=0;
#20;

//READ BACK TEST
addr=8'h43;
write=0;
transfer=1;
#40;
transfer=0;
#20;



$finish;

end
endmodule

APB/apb.vcd
$date
	Sat Sep  5 05:28:17 2026
$end
$version
	Icarus Verilog
$end
$timescale
	1s
$end
$scope module apb_tb $end
$var wire 1 ! psel0 $end
$var wire 1 " psel1 $end
$var wire 8 # read_out [7:0] $end
$var wire 1 $ pwrite $end
$var wire 8 % pwdata [7:0] $end
$var wire 1 & psel $end
$var wire 1 ' pready1 $end
$var wire 1 ( pready0 $end
$var wire 1 ) pready $end
$var wire 8 * prdata1 [7:0] $end
$var wire 8 + prdata0 [7:0] $end
$var wire 8 , prdata [7:0] $end
$var wire 1 - penable $end
$var wire 8 . paddr [7:0] $end
$var reg 8 / addr [7:0] $end
$var reg 1 0 clk $end
$var reg 8 1 data_in [7:0] $end
$var reg 1 2 reset $end
$var reg 1 3 transfer $end
$var reg 1 4 write $end
$scope module dut $end
$var wire 8 5 addr [7:0] $end
$var wire 1 0 clk $end
$var wire 8 6 data_in [7:0] $end
$var wire 8 7 prdata [7:0] $end
$var wire 1 ) pready $end
$var wire 1 2 reset $end
$var wire 1 3 transfer $end
$var wire 1 4 write $end
$var parameter 2 8 ACCESS $end
$var parameter 2 9 IDLE $end
$var parameter 2 : SETUP $end
$var reg 2 ; nextstate [1:0] $end
$var reg 8 < paddr [7:0] $end
$var reg 1 - penable $end
$var reg 1 & psel $end
$var reg 8 = pwdata [7:0] $end
$var reg 1 $ pwrite $end
$var reg 8 > read_out [7:0] $end
$var reg 2 ? state [1:0] $end
$upscope $end
$scope module dut1 $end
$var wire 1 0 clk $end
$var wire 8 @ paddr [7:0] $end
$var wire 1 - penable $end
$var wire 1 ! psel $end
$var wire 8 A pwdata [7:0] $end
$var wire 1 $ pwrite $end
$var wire 1 2 reset $end
$var reg 8 B prdata1 [7:0] $end
$var reg 1 ( pready1 $end
$var integer 32 C i [31:0] $end
$upscope $end
$scope module dut2 $end
$var wire 1 0 clk $end
$var wire 8 D paddr [7:0] $end
$var wire 1 - penable $end
$var wire 1 " psel $end
$var wire 8 E pwdata [7:0] $end
$var wire 1 $ pwrite $end
$var wire 1 2 reset $end
$var reg 8 F prdata2 [7:0] $end
$var reg 1 ' pready2 $end
$var integer 32 G i [31:0] $end
$upscope $end
$upscope $end
$enddefinitions $end
$comment Show the parameter values. $end
$dumpall
b1 :
b0 9
b10 8
$end
#0
$dumpvars
b100000000 G
b0 F
b0 E
b0 D
b100000000 C
b0 B
b0 A
b0 @
bx ?
bx >
b0 =
b0 <
b0 ;
b0 7
b0 6
b0 5
04
03
12
b0 1
00
b0 /
b0 .
0-
b0 ,
b0 +
b0 *
0)
0(
0'
0&
b0 %
0$
bx #
0"
0!
$end
#10
b0 #
b0 >
b0 ?
b100000000 C
b100000000 G
10
#20
b1 ;
00
13
14
b1110111 1
b1110111 6
b10100101 /
b10100101 5
02
#30
1"
0!
b1110111 %
b1110111 =
b1110111 A
b1110111 E
b10100101 .
b10100101 <
b10100101 @
b10100101 D
1$
1&
b10 ;
b1 ?
10
#40
00
#50
b1 ;
1)
1'
1-
b1110111 %
b1110111 =
b1110111 A
b1110111 E
b10100101 .
b10100101 <
b10100101 @
b10100101 D
1$
1&
b10 ?
10
#60
b0 ;
00
03
#70
0)
0"
0'
b0 %
b0 =
b0 A
b0 E
b0 .
b0 <
b0 @
b0 D
0$
0-
0&
b0 ?
10
#80
b1 ;
00
13
04
#90
1"
0!
b1110111 %
b1110111 =
b1110111 A
b1110111 E
b10100101 .
b10100101 <
b10100101 @
b10100101 D
1&
b10 ;
b1 ?
10
#100
00
#110
b1 ;
b1110111 ,
b1110111 7
1)
b1110111 *
b1110111 F
1'
1-
b1110111 %
b1110111 =
b1110111 A
b1110111 E
b10100101 .
b10100101 <
b10100101 @
b10100101 D
1&
b10 ?
10
#120
b0 ;
00
03
#130
0)
b0 ,
b0 7
b0 *
b0 F
0'
0"
b0 %
b0 =
b0 A
b0 E
b0 .
b0 <
b0 @
b0 D
0-
0&
b1110111 #
b1110111 >
b0 ?
10
#140
b1 ;
00
13
14
b100001 1
b100001 6
b1000011 /
b1000011 5
#150
1!
b100001 %
b100001 =
b100001 A
b100001 E
b1000011 .
b1000011 <
b1000011 @
b1000011 D
1$
1&
b10 ;
b1 ?
10
#160
00
#170
b1 ;
1)
1(
1-
b100001 %
b100001 =
b100001 A
b100001 E
b1000011 .
b1000011 <
b1000011 @
b1000011 D
1$
1&
b10 ?
10
#180
b0 ;
00
03
#190
0)
0!
0(
b0 %
b0 =
b0 A
b0 E
b0 .
b0 <
b0 @
b0 D
0$
0-
0&
b0 ?
10
#200
b1 ;
00
13
04
#210
1!
b100001 %
b100001 =
b100001 A
b100001 E
b1000011 .
b1000011 <
b1000011 @
b1000011 D
1&
b10 ;
b1 ?
10
#220
00
#230
b1 ;
b100001 ,
b100001 7
1)
b100001 +
b100001 B
1(
1-
b100001 %
b100001 =
b100001 A
b100001 E
b1000011 .
b1000011 <
b1000011 @
b1000011 D
1&
b10 ?
10
#240
b0 ;
00
03
#250
0)
b0 ,
b0 7
b0 +
b0 B
0(
0!
b0 %
b0 =
b0 A
b0 E
b0 .
b0 <
b0 @
b0 D
0-
0&
b100001 #
b100001 >
b0 ?
10
