APB/apb_slave.v
module apb_slave(
input clk,
input reset,
input psel,
input penable,
input [7:0] paddr,
input [7:0] pwdata,
input pwrite,

output reg pready,
output reg [7:0] prdata
);

reg [7:0] mem[0:255];

integer i;

always @(posedge clk) begin
    if(reset) begin
        for(i=0; i<256; i=i+1)
            mem[i] <= 8'b0;
    end
    else if(psel && penable && pwrite) begin
        mem[paddr] <= pwdata;
    end
end

always @(*) begin
    pready = 1'b0;
    prdata = 8'b0;

    if(psel && penable) begin
        pready = 1'b1;

        if(!pwrite)
            prdata = mem[paddr];
    end
end

endmodule

APB/apb_master.v
module apb_master(
input clk,
input reset,
input write,
input transfer,
input [7:0] addr,
input [7:0] data_in,

input pready,
input [7:0] prdata,


output reg psel,penable,pwrite,
output reg [7:0] paddr,
output reg [7:0] pwdata,
output reg [7:0] read_out
);

localparam IDLE =2'b00,SETUP=2'b01,ACCESS=2'b10;

reg [1:0] state,nextstate;

// STATE LOGIC
always @(posedge clk) begin
if(reset)  begin
state<=IDLE;
read_out<=8'b0;
end

else begin
state<=nextstate;
if(state==ACCESS && pready && !pwrite)
	read_out<=prdata;
end
end

//NEXTSTATE LOGIC
always @(*) begin
case(state)
IDLE: begin
if(transfer) 
nextstate=SETUP;
else
nextstate=IDLE;
end
SETUP: begin
nextstate=ACCESS;
end
ACCESS: begin
if(pready) begin
if(transfer)
nextstate=SETUP;
else
nextstate=IDLE;
end
else 
nextstate=ACCESS;
end
default:
	nextstate=IDLE;
endcase
end

//OUTPUT LOGIC
always @(*) begin
    psel    = 0;
    penable = 0;
    pwrite  = 0;
    paddr   = 0;
    pwdata  = 0;

    case(state)
        IDLE: begin
            psel = 0;
            penable = 0;
        end

        SETUP: begin
            psel = 1;
            penable = 0;
            pwrite = write;
            paddr = addr;
            pwdata = data_in;
        end

        ACCESS: begin
            psel = 1;
            penable = 1;
            pwrite = write;
            paddr = addr;
            pwdata = data_in;
        end
	default: begin
		psel=0;
		penable=0;
	end

    endcase
end
endmodule

APB/apb_tb.v
`timescale 1ns/1ps

module apb_tb;

reg        clk;
reg        reset;
reg        write;
reg        transfer;
reg  [7:0] addr;
reg  [7:0] data_in;

wire       pready;
wire [7:0] prdata;

wire       psel;
wire       penable;
wire       pwrite;
wire [7:0] paddr;
wire [7:0] pwdata;

wire [7:0] read_out;

apb_master master (
    .clk       (clk),
    .reset     (reset),
    .write     (write),
    .transfer  (transfer),
    .addr      (addr),
    .data_in   (data_in),
    .pready    (pready),
    .prdata    (prdata),
    .psel      (psel),
    .penable   (penable),
    .pwrite    (pwrite),
    .paddr     (paddr),
    .pwdata    (pwdata),
    .read_out  (read_out)
);

apb_slave slave (
    .clk       (clk),
    .reset     (reset),
    .psel      (psel),
    .penable   (penable),
    .paddr     (paddr),
    .pwdata    (pwdata),
    .pwrite    (pwrite),
    .pready    (pready),
    .prdata    (prdata)
);

initial begin
    clk = 0;
    forever #5 clk = ~clk;
end

initial begin

    reset    = 1;
    write    = 0;
    transfer = 0;
    addr     = 8'h00;
    data_in  = 8'h00;

    #20;
    reset = 0;

    @(posedge clk);

    addr     <= 8'h10;
    data_in  <= 8'hAB;
    write    <= 1'b1;
    transfer <= 1'b1;

    @(posedge clk);

    transfer <= 1'b0;

    wait(pready);

    @(posedge clk);

    addr     <= 8'h10;
    write    <= 1'b0;
    transfer <= 1'b1;

    @(posedge clk);

    transfer <= 1'b0;

    wait(pready);

    @(posedge clk);

    $display("--------------------------------");
    $display("READ TEST");
    $display("Address  = %h", addr);
    $display("Read Data = %h", read_out);
    $display("--------------------------------");

    @(posedge clk);

    addr     <= 8'h20;
    data_in  <= 8'h55;
    write    <= 1'b1;
    transfer <= 1'b1;

    @(posedge clk);

    transfer <= 1'b0;

    wait(pready);

    @(posedge clk);

    addr     <= 8'h20;
    write    <= 1'b0;
    transfer <= 1'b1;

    @(posedge clk);

    transfer <= 1'b0;

    wait(pready);

    @(posedge clk);

    $display("--------------------------------");
    $display("READ TEST");
    $display("Address  = %h", addr);
    $display("Read Data = %h", read_out);
    $display("--------------------------------");

    #20;

    $finish;

end

initial begin
    $dumpfile("apb_wave.vcd");
    $dumpvars(0, apb_tb);
end

endmodule

APB/apb_wave.vcd
$date
	Fri Sep  4 05:56:43 2026
$end
$version
	Icarus Verilog
$end
$timescale
	1ps
$end
$scope module apb_tb $end
$var wire 8 ! read_out [7:0] $end
$var wire 1 " pwrite $end
$var wire 8 # pwdata [7:0] $end
$var wire 1 $ psel $end
$var wire 1 % pready $end
$var wire 8 & prdata [7:0] $end
$var wire 1 ' penable $end
$var wire 8 ( paddr [7:0] $end
$var reg 8 ) addr [7:0] $end
$var reg 1 * clk $end
$var reg 8 + data_in [7:0] $end
$var reg 1 , reset $end
$var reg 1 - transfer $end
$var reg 1 . write $end
$scope module master $end
$var wire 8 / addr [7:0] $end
$var wire 1 * clk $end
$var wire 8 0 data_in [7:0] $end
$var wire 1 , reset $end
$var wire 1 - transfer $end
$var wire 1 . write $end
$var wire 1 % pready $end
$var wire 8 1 prdata [7:0] $end
$var parameter 2 2 ACCESS $end
$var parameter 2 3 IDLE $end
$var parameter 2 4 SETUP $end
$var reg 2 5 nextstate [1:0] $end
$var reg 8 6 paddr [7:0] $end
$var reg 1 ' penable $end
$var reg 1 $ psel $end
$var reg 8 7 pwdata [7:0] $end
$var reg 1 " pwrite $end
$var reg 8 8 read_out [7:0] $end
$var reg 2 9 state [1:0] $end
$upscope $end
$scope module slave $end
$var wire 1 * clk $end
$var wire 8 : paddr [7:0] $end
$var wire 1 ' penable $end
$var wire 1 $ psel $end
$var wire 8 ; pwdata [7:0] $end
$var wire 1 " pwrite $end
$var wire 1 , reset $end
$var reg 8 < prdata [7:0] $end
$var reg 1 % pready $end
$var integer 32 = i [31:0] $end
$upscope $end
$upscope $end
$enddefinitions $end
$comment Show the parameter values. $end
$dumpall
b1 4
b0 3
b10 2
$end
#0
$dumpvars
bx =
b0 <
b0 ;
b0 :
bx 9
bx 8
b0 7
b0 6
b0 5
b0 1
b0 0
b0 /
0.
0-
1,
b0 +
0*
b0 )
b0 (
0'
b0 &
0%
0$
b0 #
0"
bx !
$end
#5000
b0 !
b0 8
b0 9
b100000000 =
1*
#10000
0*
#15000
b100000000 =
1*
#20000
0*
0,
#25000
b1 5
1-
1.
b10101011 +
b10101011 0
b10000 )
b10000 /
1*
#30000
0*
#35000
b10101011 #
b10101011 7
b10101011 ;
b10000 (
b10000 6
b10000 :
1"
1$
b10 5
0-
b1 9
1*
#40000
0*
#45000
b0 5
1%
1'
b10101011 #
b10101011 7
b10101011 ;
b10000 (
b10000 6
b10000 :
1"
1$
b10 9
1*
#50000
0*
#55000
0%
b1 5
b0 #
b0 7
b0 ;
b0 (
b0 6
b0 :
0"
0'
0$
b0 9
1-
0.
1*
#60000
0*
#65000
b10101011 #
b10101011 7
b10101011 ;
b10000 (
b10000 6
b10000 :
1$
b10 5
0-
b1 9
1*
#70000
0*
#75000
b0 5
b10101011 &
b10101011 1
b10101011 <
1%
1'
b10101011 #
b10101011 7
b10101011 ;
b10000 (
b10000 6
b10000 :
1$
b10 9
1*
#80000
0*
#85000
b0 &
b0 1
b0 <
0%
b0 #
b0 7
b0 ;
b0 (
b0 6
b0 :
0'
0$
b10101011 !
b10101011 8
b0 9
1*
#90000
0*
#95000
b1 5
1-
1.
b1010101 +
b1010101 0
b100000 )
b100000 /
1*
#100000
0*
#105000
b1010101 #
b1010101 7
b1010101 ;
b100000 (
b100000 6
b100000 :
1"
1$
b10 5
b1 9
0-
1*
#110000
0*
#115000
b0 5
1%
1'
b1010101 #
b1010101 7
b1010101 ;
b100000 (
b100000 6
b100000 :
1"
1$
b10 9
1*
#120000
0*
#125000
0%
b1 5
b0 #
b0 7
b0 ;
b0 (
b0 6
b0 :
0"
0'
0$
b0 9
1-
0.
1*
#130000
0*
#135000
b1010101 #
b1010101 7
b1010101 ;
b100000 (
b100000 6
b100000 :
1$
b10 5
0-
b1 9
1*
#140000
0*
#145000
b0 5
b1010101 &
b1010101 1
b1010101 <
1%
1'
b1010101 #
b1010101 7
b1010101 ;
b100000 (
b100000 6
b100000 :
1$
b10 9
1*
#150000
0*
#155000
b0 &
b0 1
b0 <
0%
b0 #
b0 7
b0 ;
b0 (
b0 6
b0 :
0'
0$
b1010101 !
b1010101 8
b0 9
1*
