i2c_master/i2c_master_read.v
module read(input clk_50mhz, 
input reset, 
input start, 
input [6:0]slave_addr, 
input [7:0]pointer_addr, 
output reg [7:0]data_out, 
output reg busy, 
output reg done, 
inout scl, 
inout sda 
); 
 
reg [7:0]clk_count; 
reg timing_tick; 
 
reg sda_oe; 
reg scl_oe; 
 
assign scl=scl_oe?1'b0:1'bz; 
assign sda=sda_oe?1'b0:1'bz; 
 
reg [7:0]addr_reg; 
reg [7:0]pointer_reg; 
reg [7:0]read_data_reg; 
reg [3:0]bit_count; 
reg scl_phase; 
 
 parameter IDLE= 4'd0; 
 parameter START = 4'd1; 
 parameter SLAVE_ADDR_W  = 4'd2; 
 parameter SLAVE_ACK_W = 4'd3; 
 parameter POINTER_ADDR = 4'd4; 
 parameter POINTER_ACK = 4'd5; 
 parameter REPEATED_START = 4'd6; 
 parameter SLAVE_ADDR_R = 4'd7; 
 parameter SLAVE_ACK_R = 4'd8; 
 parameter READ_DATA = 4'd9; 
 parameter MASTER_NACK = 4'd10; 
 parameter STOP = 4'd11; 
 parameter DONE_STATE = 4'd12; 
 
reg [3:0]state; 
reg [3:0]next_state; 
 
always@(posedge clk_50mhz or posedge reset)begin 
if(reset) begin 
	clk_count<=8'd0; 
	timing_tick<=1'b0; 
end 
else begin 
	timing_tick<=1'b0; 
	if(clk_count==8'd249)begin 
		clk_count<=8'd0; 
		timing_tick<=1'b1; 
	end 
	else begin 
		clk_count<=clk_count+1'b1; 
	end 
end 
end 
 
always@(posedge clk_50mhz or posedge reset)begin 
	if(reset) begin 
		state<=IDLE; 
		addr_reg<=8'd0; 
		pointer_reg<=8'd0; 
		read_data_reg<=8'd0; 
		data_out<=8'd0; 
		bit_count<=4'd7; 
		scl_phase<=1'b0; 
		busy<=1'b0; 
		done<=1'b0; 
	end 
	else begin 
		if(timing_tick)begin 
		state <=next_state; 
		case(state) 
			IDLE: begin 
				scl_phase<=1'b0; 
				done<=1'b0; 
				if(start) begin 
					addr_reg<={slave_addr,1'b0}; 
					pointer_reg<=pointer_addr; 
					bit_count<=4'd7; 
					busy<=1'b1; 
					done<=1'b0; 
				end 
			end 
 
			START:begin 
				scl_phase<=1'b0; 
				bit_count<=4'd7; 
			end 
 
			SLAVE_ADDR_W:begin 
				if(scl_phase==1'b0)begin 
					scl_phase<=1'b1; 
				end 
				else begin 
					scl_phase<=1'b0; 
					if(bit_count!=0) 
						bit_count<=bit_count-1'b1; 
					else 
						bit_count<=4'd7; 
				end 
			end 
 
			SLAVE_ACK_W:begin 
				if(scl_phase==1'b0) 
					scl_phase<=1'b1; 
				else 
					scl_phase<=1'b0; 
			end 
 
			POINTER_ADDR:begin 
				if(scl_phase==1'b0) begin 
					scl_phase<=1'b1; 
				end 
				else begin 
					scl_phase<=1'b0; 
					if(bit_count !=0) 
						bit_count<=bit_count-1'b1; 
					else 
						bit_count<=4'd7; 
				end 
			end 
 
			POINTER_ACK:begin 
				if(scl_phase==1'b0) 
					scl_phase<=1'b1; 
				else begin 
					scl_phase<=1'b0; 
					addr_reg<={addr_reg[7:1],1'b1}; 
				end 
			end 
 
			REPEATED_START:begin 
				if(scl_phase==1'b0)begin 
					scl_phase<=1'b1; 
				end 
				else begin 
					scl_phase<=1'b0; 
					bit_count<=4'd7; 
				end 
			end 
 
			SLAVE_ADDR_R:begin 
                        if (scl_phase == 1'b0)begin 
                            scl_phase <= 1'b1; 
                        end 
                        else begin 
                            scl_phase <= 1'b0; 
 
                            if (bit_count != 0) 
                                bit_count <= bit_count - 1'b1; 
                            else 
                                bit_count <= 4'd7; 
                        end 
            end 
 
			SLAVE_ACK_R:begin 
                        if (scl_phase == 1'b0) 
                            scl_phase <= 1'b1; 
                        else 
                            scl_phase <= 1'b0; 
            end 
 
			 READ_DATA:begin 
                        if (scl_phase == 1'b0)begin 
                        scl_phase <= 1'b1; 
                        end 
                        else begin 
                            read_data_reg[bit_count] <= sda; 
                            scl_phase <= 1'b0; 
                            if (bit_count != 0) 
                            begin 
                                bit_count <= bit_count - 1'b1; 
                            end 
                            else 
                            begin 
                                bit_count <= 4'd7; 
                            end 
                        end 
                    end 
 
 
                    MASTER_NACK:begin 
			    if (scl_phase == 1'b0) begin 
                            scl_phase <= 1'b1; 
                        end 
                        else begin 
                            scl_phase <= 1'b0; 
                            data_out <= read_data_reg; 
                        end 
                    end 
 
                    STOP: 
                    begin 
                        if (scl_phase == 1'b0) 
                        begin 
                            scl_phase <= 1'b1; 
                        end 
                        else 
                        begin 
                            scl_phase <= 1'b0; 
                            busy <= 1'b0; 
                        end 
                    end 
 
                    DONE_STATE: 
                    begin 
                        busy <= 1'b0; 
                        done <= 1'b1; 
                    end 
 
 
                    default: 
                    begin 
                        scl_phase <= 1'b0; 
 
                        busy <= 1'b0; 
                        done <= 1'b0; 
                    end 
 
                endcase 
            end 
    end 
    end 
 
    always@(*) begin 
	next_state=state; 
    case(state) 
 
	    IDLE:begin 
		    if(start) 
			    next_state=START; 
		    else 
			    next_state=IDLE; 
	    end 
 
	    START:begin 
		    next_state=SLAVE_ADDR_W; 
	    end 
 
	    SLAVE_ADDR_W:begin 
		    if((scl_phase==1'b1)&&(bit_count==4'd0))begin 
			    next_state=SLAVE_ACK_W; 
		    end 
		    else begin 
			    next_state=SLAVE_ADDR_W; 
		    end 
	    end 
 
	    SLAVE_ACK_W:begin 
		    if(scl_phase==1'b1)begin 
			    if(sda==1'b0) 
				    next_state=POINTER_ADDR; 
			    else  
				    next_state=STOP; 
		    end 
		    else begin 
			    next_state=SLAVE_ACK_W; 
		    end 
	    end 
 
	    POINTER_ADDR:begin 
		    if((scl_phase==1'b1)&&(bit_count==4'd0))begin 
			    next_state=POINTER_ACK; 
		    end 
		    else begin 
			    next_state=POINTER_ADDR; 
		    end 
	    end 
 
	    POINTER_ACK:begin 
		    if(scl_phase==1'b1)begin 
			    if(sda==1'b0) 
				    next_state=REPEATED_START; 
			    else 
				    next_state=STOP; 
		    end 
		    else begin 
			    next_state=POINTER_ACK; 
		    end 
	    end 
 
	    REPEATED_START:begin 
		    if(scl_phase==1'b1) 
			    next_state=SLAVE_ADDR_R; 
		    else 
			    next_state=REPEATED_START; 
	    end 
 
	    SLAVE_ADDR_R:begin 
		    if((scl_phase==1'b1)&&(bit_count==4'd0))begin 
			    next_state=SLAVE_ACK_R; 
		    end 
		    else begin 
			    next_state=SLAVE_ADDR_R; 
		    end 
	    end 
 
	    SLAVE_ACK_R:begin 
		    if(scl_phase==1'b1)begin 
			    if(sda==1'b0) 
				    next_state=READ_DATA; 
			    else 
				    next_state=STOP; 
		    end 
		    else begin 
			    next_state=SLAVE_ACK_R; 
		    end 
	    end 
 
	    READ_DATA:begin 
		    if((scl_phase==1'b1)&&(bit_count==4'd0))begin 
			    next_state=MASTER_NACK; 
		    end 
		    else begin 
			    next_state=READ_DATA; 
		    end 
	    end 
 
	    MASTER_NACK:begin 
		    if(scl_phase==1'b1) 
			    next_state=STOP; 
		    else 
			    next_state=MASTER_NACK; 
	    end 
	     
	    STOP:begin 
		    if(scl_phase==1'b1) 
			    next_state=DONE_STATE; 
		    else  
			    next_state=STOP; 
	    end 
 
	    DONE_STATE:begin 
		    next_state=IDLE; 
	    end 
 
	    default: begin 
		    next_state=IDLE; 
	    end 
    endcase 
    end 
 
    always@(*) begin 
	    scl_oe=1'b0; 
	    sda_oe=1'b0; 
	    case(state) 
		    IDLE:begin 
			    scl_oe=1'b0; 
			    sda_oe=1'b0; 
		    end 
 
		    START:begin 
			    scl_oe=1'b0; 
			    sda_oe=1'b1; 
		    end 
 
		    SLAVE_ADDR_W:begin 
			    if(scl_phase==1'b0) 
				    scl_oe=1'b1; 
			    else 
				    scl_oe=1'b0; 
			    if(addr_reg[bit_count]==1'b0) 
				    sda_oe=1'b1; 
			    else 
				    sda_oe=1'b0; 
		    end 
 
		    SLAVE_ACK_W:begin 
			    if(scl_phase==1'b0) 
				    scl_oe=1'b1; 
			    else 
				    scl_oe=1'b0; 
			    sda_oe=1'b0; 
		    end 
 
		    POINTER_ADDR:begin 
			    if(scl_phase==1'b0) 
				    scl_oe=1'b1; 
			    else 
				    scl_oe=1'b0; 
			    if(pointer_reg[bit_count]==1'b0) 
				    sda_oe=1'b1; 
			    else 
				    sda_oe=1'b0; 
		    end 
 
		    POINTER_ACK:begin 
			    if(scl_phase==1'b0) 
				    scl_oe=1'b1; 
			    else 
				    scl_oe=1'b0; 
			    sda_oe=1'b0; 
		    end 
 
		    REPEATED_START:begin 
			    if(scl_phase==1'b0)begin 
				    scl_oe=1'b1; 
				    sda_oe=1'b0; 
			    end 
			    else begin 
				    scl_oe=1'b0; 
				    sda_oe=1'b1; 
			    end 
		    end 
 
		    SLAVE_ADDR_R:begin 
			    if(scl_phase==1'b0) 
				    scl_oe=1'b1; 
			    else 
				    scl_oe=1'b0; 
			    if(addr_reg[bit_count]==1'b0) 
				    sda_oe=1'b1; 
			    else 
				    sda_oe=1'b0; 
		    end 
 
		    SLAVE_ACK_R:begin 
			    if(scl_phase==1'b0) 
				    scl_oe=1'b1; 
			    else 
				    scl_oe=1'b0; 
			    sda_oe=1'b0; 
		    end 
 
		    READ_DATA:begin 
			    if(scl_phase==1'b0) 
				    scl_oe=1'b1; 
			    else 
				    scl_oe=1'b0; 
			    sda_oe=1'b0; 
		    end 
 
		    MASTER_NACK:begin 
			    if(scl_phase==1'b0) 
				    scl_oe=1'b1; 
			    else 
				    scl_oe=1'b0; 
			    sda_oe=1'b0; 
		    end 
 
		    STOP:begin 
			    if(scl_phase==1'b0)begin 
				    scl_oe=1'b1; 
				    sda_oe=1'b1; 
			    end 
			    else begin 
				    scl_oe=1'b0; 
				    sda_oe=1'b0; 
			    end 
		    end 
 
		    DONE_STATE:begin 
			    scl_oe=1'b0; 
			    sda_oe=1'b0; 
		    end 
 
		    default:begin 
			    scl_oe=1'b0; 
			    sda_oe=1'b0; 
		    end 
	    endcase 
    end 
    endmodule

I2C/i2c_master_rd_tb.v
`timescale 1ns/1ps

module i2c_read_tb;

reg clk_50mhz;
reg reset;
reg start;

reg [6:0] slave_addr;
reg [7:0] pointer_addr;

wire [7:0] data_out;
wire busy;
wire done;

wire scl;
wire sda;

reg slave_sda_oe;

reg [7:0] slave_read_data;


read uut (
    .clk_50mhz    (clk_50mhz),
    .reset        (reset),
    .start        (start),
    .slave_addr   (slave_addr),
    .pointer_addr (pointer_addr),
    .data_out     (data_out),
    .busy         (busy),
    .done         (done),
    .scl          (scl),
    .sda          (sda)
);


pullup(scl);
pullup(sda);

assign sda = slave_sda_oe ? 1'b0 : 1'bz;
    
initial begin

    clk_50mhz = 1'b0;

    forever #10 clk_50mhz = ~clk_50mhz;

end


always @(*) begin

    slave_sda_oe = 1'b0;

    case(uut.state)

        uut.SLAVE_ACK_W:
        begin
            slave_sda_oe = 1'b1;
        end

        uut.POINTER_ACK:
        begin
            slave_sda_oe = 1'b1;
        end

        uut.SLAVE_ACK_R:
        begin
            slave_sda_oe = 1'b1;
        end
        uut.READ_DATA:
        begin
            if(slave_read_data[uut.bit_count] == 1'b0)
                slave_sda_oe = 1'b1;
            else
                slave_sda_oe = 1'b0;

        end

        default:
        begin
            slave_sda_oe = 1'b0;
        end

    endcase

end


initial begin

    reset = 1'b1;
    start = 1'b0;

    slave_addr   = 7'h57;
    pointer_addr = 8'h2A;

    slave_read_data = 8'hA5;

    #100;

    reset = 1'b0;

    #100;

  start = 1'b1;

    #6000;

    start = 1'b0;


    wait(uut.state == uut.START);

    $display("-----------------------------------------");
    $display("START detected");
    $display("-----------------------------------------");


    wait(uut.state == uut.SLAVE_ADDR_W);

    $display("-----------------------------------------");
    $display("Slave receiving WRITE address");
    $display("-----------------------------------------");

    wait(uut.state == uut.SLAVE_ACK_W);

    $display("Slave ACK WRITE address");

    wait(uut.state == uut.POINTER_ADDR);

    $display("-----------------------------------------");
    $display("Slave receiving POINTER address");
    $display("-----------------------------------------");

    wait(uut.state == uut.POINTER_ACK);

    $display("Slave ACK POINTER address");

    wait(uut.state == uut.REPEATED_START);

    $display("-----------------------------------------");
    $display("REPEATED START detected");
    $display("-----------------------------------------");

    wait(uut.state == uut.SLAVE_ADDR_R);

    $display("-----------------------------------------");
    $display("Slave receiving READ address");
    $display("-----------------------------------------");

    wait(uut.state == uut.SLAVE_ACK_R);

    $display("Slave ACK READ address");

    wait(uut.state == uut.READ_DATA);

    $display("-----------------------------------------");
    $display("Slave sending data = %h",
             slave_read_data);
    $display("-----------------------------------------");

    wait(uut.state == uut.MASTER_NACK);

    $display("-----------------------------------------");
    $display("Master NACK");
    $display("-----------------------------------------");

    wait(uut.state == uut.STOP);

    $display("-----------------------------------------");
    $display("STOP detected");
    $display("-----------------------------------------");

    wait(done == 1'b1);
    $display("-----------------------------------------");
    $display("I2C READ TRANSACTION COMPLETED");
    $display("-----------------------------------------");


    if(data_out == slave_read_data)
    begin

        $display("-----------------------------------------");
        $display("READ TEST PASSED");
        $display("Expected data = %h",
                 slave_read_data);
        $display("Received data = %h",
                 data_out);
        $display("-----------------------------------------");

    end
    else
    begin

        $display("-----------------------------------------");
        $display("READ TEST FAILED");
        $display("Expected data = %h",
                 slave_read_data);
        $display("Received data = %h",
                 data_out);
        $display("-----------------------------------------");

    end


    #100;

    $finish;

end


initial begin

    $monitor(
        "TIME=%0t | TICK=%b | START=%b | STATE=%0d | NEXT=%0d | PHASE=%b | SCL=%b | SDA=%b | BIT=%0d | BUSY=%b | DONE=%b | DATA=%h",
        $time,
        uut.timing_tick,
        start,
        uut.state,
        uut.next_state,
        uut.scl_phase,
        scl,
        sda,
        uut.bit_count,
        busy,
        done,
        data_out
    );

end


initial begin

    $dumpfile("i2c_read.vcd");

    $dumpvars(0, i2c_read_tb);

end

endmodule

I2C/i2c_read.vcd
$date
	Tue Sep  1 03:48:52 2026
$end
$version
	Icarus Verilog
$end
$timescale
	1ps
$end
$scope module i2c_read_tb $end
$var wire 1 ! scl $end
$var wire 1 " sda $end
$var wire 1 # done $end
$var wire 8 $ data_out [7:0] $end
$var wire 1 % busy $end
$var reg 1 & clk_50mhz $end
$var reg 8 ' pointer_addr [7:0] $end
$var reg 1 ( reset $end
$var reg 7 ) slave_addr [6:0] $end
$var reg 8 * slave_read_data [7:0] $end
$var reg 1 + slave_sda_oe $end
$var reg 1 , start $end
$scope module uut $end
$var wire 1 & clk_50mhz $end
$var wire 8 - pointer_addr [7:0] $end
$var wire 1 ( reset $end
$var wire 1 ! scl $end
$var wire 1 " sda $end
$var wire 7 . slave_addr [6:0] $end
$var wire 1 , start $end
$var parameter 4 / DONE_STATE $end
$var parameter 4 0 IDLE $end
$var parameter 4 1 MASTER_NACK $end
$var parameter 4 2 POINTER_ACK $end
$var parameter 4 3 POINTER_ADDR $end
$var parameter 4 4 READ_DATA $end
$var parameter 4 5 REPEATED_START $end
$var parameter 4 6 SLAVE_ACK_R $end
$var parameter 4 7 SLAVE_ACK_W $end
$var parameter 4 8 SLAVE_ADDR_R $end
$var parameter 4 9 SLAVE_ADDR_W $end
$var parameter 4 : START $end
$var parameter 4 ; STOP $end
$var reg 8 < addr_reg [7:0] $end
$var reg 4 = bit_count [3:0] $end
$var reg 1 % busy $end
$var reg 8 > clk_count [7:0] $end
$var reg 8 ? data_out [7:0] $end
$var reg 1 # done $end
$var reg 4 @ next_state [3:0] $end
$var reg 8 A pointer_reg [7:0] $end
$var reg 8 B read_data_reg [7:0] $end
$var reg 1 C scl_oe $end
$var reg 1 D scl_phase $end
$var reg 1 E sda_oe $end
$var reg 4 F state [3:0] $end
$var reg 1 G timing_tick $end
$upscope $end
$upscope $end
$enddefinitions $end
$comment Show the parameter values. $end
$dumpall
b1011 ;
b1 :
b10 9
b111 8
b11 7
b1000 6
b110 5
b1001 4
b100 3
b101 2
b1010 1
b0 0
b1100 /
$end
#0
$dumpvars
0G
b0 F
0E
0D
0C
b0 B
b0 A
b0 @
b0 ?
b0 >
b111 =
b0 <
b1010111 .
b101010 -
0,
0+
b10100101 *
b1010111 )
1(
b101010 '
0&
0%
b0 $
0#
1"
1!
$end
#10000
1&
#20000
0&
#30000
1&
#40000
0&
#50000
1&
#60000
0&
#70000
1&
#80000
0&
#90000
1&
#100000
0&
0(
#110000
b1 >
1&
#120000
0&
#130000
b10 >
1&
#140000
0&
#150000
b11 >
1&
#160000
0&
#170000
b100 >
1&
#180000
0&
#190000
b101 >
1&
#200000
b1 @
0&
1,
#210000
b110 >
1&
#220000
0&
#230000
b111 >
1&
#240000
0&
#250000
b1000 >
1&
#260000
0&
#270000
b1001 >
1&
#280000
0&
#290000
b1010 >
1&
#300000
0&
#310000
b1011 >
1&
#320000
0&
#330000
b1100 >
1&
#340000
0&
#350000
b1101 >
1&
#360000
0&
#370000
b1110 >
1&
#380000
0&
#390000
b1111 >
1&
#400000
0&
#410000
b10000 >
1&
#420000
0&
#430000
b10001 >
1&
#440000
0&
#450000
b10010 >
1&
#460000
0&
#470000
b10011 >
1&
#480000
0&
#490000
b10100 >
1&
#500000
0&
#510000
b10101 >
1&
#520000
0&
#530000
b10110 >
1&
#540000
0&
#550000
b10111 >
1&
#560000
0&
#570000
b11000 >
1&
#580000
0&
#590000
b11001 >
1&
#600000
0&
#610000
b11010 >
1&
#620000
0&
#630000
b11011 >
1&
#640000
0&
#650000
b11100 >
1&
#660000
0&
#670000
b11101 >
1&
#680000
0&
#690000
b11110 >
1&
#700000
0&
#710000
b11111 >
1&
#720000
0&
#730000
b100000 >
1&
#740000
0&
#750000
b100001 >
1&
#760000
0&
#770000
b100010 >
1&
#780000
0&
#790000
b100011 >
1&
#800000
0&
#810000
b100100 >
1&
#820000
0&
#830000
b100101 >
1&
#840000
0&
#850000
b100110 >
1&
#860000
0&
#870000
b100111 >
1&
#880000
0&
#890000
b101000 >
1&
#900000
0&
#910000
b101001 >
1&
#920000
0&
#930000
b101010 >
1&
#940000
0&
#950000
b101011 >
1&
#960000
0&
#970000
b101100 >
1&
#980000
0&
#990000
b101101 >
1&
#1000000
0&
#1010000
b101110 >
1&
#1020000
0&
#1030000
b101111 >
1&
#1040000
0&
#1050000
b110000 >
1&
#1060000
0&
#1070000
b110001 >
1&
#1080000
0&
#1090000
b110010 >
1&
#1100000
0&
#1110000
b110011 >
1&
#1120000
0&
#1130000
b110100 >
1&
#1140000
0&
#1150000
b110101 >
1&
#1160000
0&
#1170000
b110110 >
1&
#1180000
0&
#1190000
b110111 >
1&
#1200000
0&
#1210000
b111000 >
1&
#1220000
0&
#1230000
b111001 >
1&
#1240000
0&
#1250000
b111010 >
1&
#1260000
0&
#1270000
b111011 >
1&
#1280000
0&
#1290000
b111100 >
1&
#1300000
0&
#1310000
b111101 >
1&
#1320000
0&
#1330000
b111110 >
1&
#1340000
0&
#1350000
b111111 >
1&
#1360000
0&
#1370000
b1000000 >
1&
#1380000
0&
#1390000
b1000001 >
1&
#1400000
0&
#1410000
b1000010 >
1&
#1420000
0&
#1430000
b1000011 >
1&
#1440000
0&
#1450000
b1000100 >
1&
#1460000
0&
#1470000
b1000101 >
1&
#1480000
0&
#1490000
b1000110 >
1&
#1500000
0&
#1510000
b1000111 >
1&
#1520000
0&
#1530000
b1001000 >
1&
#1540000
0&
#1550000
b1001001 >
1&
#1560000
0&
#1570000
b1001010 >
1&
#1580000
0&
#1590000
b1001011 >
1&
#1600000
0&
#1610000
b1001100 >
1&
#1620000
0&
#1630000
b1001101 >
1&
#1640000
0&
#1650000
b1001110 >
1&
#1660000
0&
#1670000
b1001111 >
1&
#1680000
0&
#1690000
b1010000 >
1&
#1700000
0&
#1710000
b1010001 >
1&
#1720000
0&
#1730000
b1010010 >
1&
#1740000
0&
#1750000
b1010011 >
1&
#1760000
0&
#1770000
b1010100 >
1&
#1780000
0&
#1790000
b1010101 >
1&
#1800000
0&
#1810000
b1010110 >
1&
#1820000
0&
#1830000
b1010111 >
1&
#1840000
0&
#1850000
b1011000 >
1&
#1860000
0&
#1870000
b1011001 >
1&
#1880000
0&
#1890000
b1011010 >
1&
#1900000
0&
#1910000
b1011011 >
1&
#1920000
0&
#1930000
b1011100 >
1&
#1940000
0&
#1950000
b1011101 >
1&
#1960000
0&
#1970000
b1011110 >
1&
#1980000
0&
#1990000
b1011111 >
1&
#2000000
0&
#2010000
b1100000 >
1&
#2020000
0&
#2030000
b1100001 >
1&
#2040000
0&
#2050000
b1100010 >
1&
#2060000
0&
#2070000
b1100011 >
1&
#2080000
0&
#2090000
b1100100 >
1&
#2100000
0&
#2110000
b1100101 >
1&
#2120000
0&
#2130000
b1100110 >
1&
#2140000
0&
#2150000
b1100111 >
1&
#2160000
0&
#2170000
b1101000 >
1&
#2180000
0&
#2190000
b1101001 >
1&
#2200000
0&
#2210000
b1101010 >
1&
#2220000
0&
#2230000
b1101011 >
1&
#2240000
0&
#2250000
b1101100 >
1&
#2260000
0&
#2270000
b1101101 >
1&
#2280000
0&
#2290000
b1101110 >
1&
#2300000
0&
#2310000
b1101111 >
1&
#2320000
0&
#2330000
b1110000 >
1&
#2340000
0&
#2350000
b1110001 >
1&
#2360000
0&
#2370000
b1110010 >
1&
#2380000
0&
#2390000
b1110011 >
1&
#2400000
0&
#2410000
b1110100 >
1&
#2420000
0&
#2430000
b1110101 >
1&
#2440000
0&
#2450000
b1110110 >
1&
#2460000
0&
#2470000
b1110111 >
1&
#2480000
0&
#2490000
b1111000 >
1&
#2500000
0&
#2510000
b1111001 >
1&
#2520000
0&
#2530000
b1111010 >
1&
#2540000
0&
#2550000
b1111011 >
1&
#2560000
0&
#2570000
b1111100 >
1&
#2580000
0&
#2590000
b1111101 >
1&
#2600000
0&
#2610000
b1111110 >
1&
#2620000
0&
#2630000
b1111111 >
1&
#2640000
0&
#2650000
b10000000 >
1&
#2660000
0&
#2670000
b10000001 >
1&
#2680000
0&
#2690000
b10000010 >
1&
#2700000
0&
#2710000
b10000011 >
1&
#2720000
0&
#2730000
b10000100 >
1&
#2740000
0&
#2750000
b10000101 >
1&
#2760000
0&
#2770000
b10000110 >
1&
#2780000
0&
#2790000
b10000111 >
1&
#2800000
0&
#2810000
b10001000 >
1&
#2820000
0&
#2830000
b10001001 >
1&
#2840000
0&
#2850000
b10001010 >
1&
#2860000
0&
#2870000
b10001011 >
1&
#2880000
0&
#2890000
b10001100 >
1&
#2900000
0&
#2910000
b10001101 >
1&
#2920000
0&
#2930000
b10001110 >
1&
#2940000
0&
#2950000
b10001111 >
1&
#2960000
0&
#2970000
b10010000 >
1&
#2980000
0&
#2990000
b10010001 >
1&
#3000000
0&
#3010000
b10010010 >
1&
#3020000
0&
#3030000
b10010011 >
1&
#3040000
0&
#3050000
b10010100 >
1&
#3060000
0&
#3070000
b10010101 >
1&
#3080000
0&
#3090000
b10010110 >
1&
#3100000
0&
#3110000
b10010111 >
1&
#3120000
0&
#3130000
b10011000 >
1&
#3140000
0&
#3150000
b10011001 >
1&
#3160000
0&
#3170000
b10011010 >
1&
#3180000
0&
#3190000
b10011011 >
1&
#3200000
0&
#3210000
b10011100 >
1&
#3220000
0&
#3230000
b10011101 >
1&
#3240000
0&
#3250000
b10011110 >
1&
#3260000
0&
#3270000
b10011111 >
1&
#3280000
0&
#3290000
b10100000 >
1&
#3300000
0&
#3310000
b10100001 >
1&
#3320000
0&
#3330000
b10100010 >
1&
#3340000
0&
#3350000
b10100011 >
1&
#3360000
0&
#3370000
b10100100 >
1&
#3380000
0&
#3390000
b10100101 >
1&
#3400000
0&
#3410000
b10100110 >
1&
#3420000
0&
#3430000
b10100111 >
1&
#3440000
0&
#3450000
b10101000 >
1&
#3460000
0&
#3470000
b10101001 >
1&
#3480000
0&
#3490000
b10101010 >
1&
#3500000
0&
#3510000
b10101011 >
1&
#3520000
0&
#3530000
b10101100 >
1&
#3540000
0&
#3550000
b10101101 >
1&
#3560000
0&
#3570000
b10101110 >
1&
#3580000
0&
#3590000
b10101111 >
1&
#3600000
0&
#3610000
b10110000 >
1&
#3620000
0&
#3630000
b10110001 >
1&
#3640000
0&
#3650000
b10110010 >
1&
#3660000
0&
#3670000
b10110011 >
1&
#3680000
0&
#3690000
b10110100 >
1&
#3700000
0&
#3710000
b10110101 >
1&
#3720000
0&
#3730000
b10110110 >
1&
#3740000
0&
#3750000
b10110111 >
1&
#3760000
0&
#3770000
b10111000 >
1&
#3780000
0&
#3790000
b10111001 >
1&
#3800000
0&
#3810000
b10111010 >
1&
#3820000
0&
#3830000
b10111011 >
1&
#3840000
0&
#3850000
b10111100 >
1&
#3860000
0&
#3870000
b10111101 >
1&
#3880000
0&
#3890000
b10111110 >
1&
#3900000
0&
#3910000
b10111111 >
1&
#3920000
0&
#3930000
b11000000 >
1&
#3940000
0&
#3950000
b11000001 >
1&
#3960000
0&
#3970000
b11000010 >
1&
#3980000
0&
#3990000
b11000011 >
1&
#4000000
0&
#4010000
b11000100 >
1&
#4020000
0&
#4030000
b11000101 >
1&
#4040000
0&
#4050000
b11000110 >
1&
#4060000
0&
#4070000
b11000111 >
1&
#4080000
0&
#4090000
b11001000 >
1&
#4100000
0&
#4110000
b11001001 >
1&
#4120000
0&
#4130000
b11001010 >
1&
#4140000
0&
#4150000
b11001011 >
1&
#4160000
0&
#4170000
b11001100 >
1&
#4180000
0&
#4190000
b11001101 >
1&
#4200000
0&
#4210000
b11001110 >
1&
#4220000
0&
#4230000
b11001111 >
1&
#4240000
0&
#4250000
b11010000 >
1&
#4260000
0&
#4270000
b11010001 >
1&
#4280000
0&
#4290000
b11010010 >
1&
#4300000
0&
#4310000
b11010011 >
1&
#4320000
0&
#4330000
b11010100 >
1&
#4340000
0&
#4350000
b11010101 >
1&
#4360000
0&
#4370000
b11010110 >
1&
#4380000
0&
#4390000
b11010111 >
1&
#4400000
0&
#4410000
b11011000 >
1&
#4420000
0&
#4430000
b11011001 >
1&
#4440000
0&
#4450000
b11011010 >
1&
#4460000
0&
#4470000
b11011011 >
1&
#4480000
0&
#4490000
b11011100 >
1&
#4500000
0&
#4510000
b11011101 >
1&
#4520000
0&
#4530000
b11011110 >
1&
#4540000
0&
#4550000
b11011111 >
1&
#4560000
0&
#4570000
b11100000 >
1&
#4580000
0&
#4590000
b11100001 >
1&
#4600000
0&
#4610000
b11100010 >
1&
#4620000
0&
#4630000
b11100011 >
1&
#4640000
0&
#4650000
b11100100 >
1&
#4660000
0&
#4670000
b11100101 >
1&
#4680000
0&
#4690000
b11100110 >
1&
#4700000
0&
#4710000
b11100111 >
1&
#4720000
0&
#4730000
b11101000 >
1&
#4740000
0&
#4750000
b11101001 >
1&
#4760000
0&
#4770000
b11101010 >
1&
#4780000
0&
#4790000
b11101011 >
1&
#4800000
0&
#4810000
b11101100 >
1&
#4820000
0&
#4830000
b11101101 >
1&
#4840000
0&
#4850000
b11101110 >
1&
#4860000
0&
#4870000
b11101111 >
1&
#4880000
0&
#4890000
b11110000 >
1&
#4900000
0&
#4910000
b11110001 >
1&
#4920000
0&
#4930000
b11110010 >
1&
#4940000
0&
#4950000
b11110011 >
1&
#4960000
0&
#4970000
b11110100 >
1&
#4980000
0&
#4990000
b11110101 >
1&
#5000000
0&
#5010000
b11110110 >
1&
#5020000
0&
#5030000
b11110111 >
1&
#5040000
0&
#5050000
b11111000 >
1&
#5060000
0&
#5070000
b11111001 >
1&
#5080000
0&
#5090000
1G
b0 >
1&
#5100000
0&
#5110000
0"
1E
b10 @
b1 >
0G
1%
b101010 A
b10101110 <
b1 F
1&
#5120000
0&
#5130000
b10 >
1&
#5140000
0&
#5150000
b11 >
1&
#5160000
0&
#5170000
b100 >
1&
#5180000
0&
#5190000
b101 >
1&
#5200000
0&
#5210000
b110 >
1&
#5220000
0&
#5230000
b111 >
1&
#5240000
0&
#5250000
b1000 >
1&
#5260000
0&
#5270000
b1001 >
1&
#5280000
0&
#5290000
b1010 >
1&
#5300000
0&
#5310000
b1011 >
1&
#5320000
0&
#5330000
b1100 >
1&
#5340000
0&
#5350000
b1101 >
1&
#5360000
0&
#5370000
b1110 >
1&
#5380000
0&
#5390000
b1111 >
1&
#5400000
0&
#5410000
b10000 >
1&
#5420000
0&
#5430000
b10001 >
1&
#5440000
0&
#5450000
b10010 >
1&
#5460000
0&
#5470000
b10011 >
1&
#5480000
0&
#5490000
b10100 >
1&
#5500000
0&
#5510000
b10101 >
1&
#5520000
0&
#5530000
b10110 >
1&
#5540000
0&
#5550000
b10111 >
1&
#5560000
0&
#5570000
b11000 >
1&
#5580000
0&
#5590000
b11001 >
1&
#5600000
0&
#5610000
b11010 >
1&
#5620000
0&
#5630000
b11011 >
1&
#5640000
0&
#5650000
b11100 >
1&
#5660000
0&
#5670000
b11101 >
1&
#5680000
0&
#5690000
b11110 >
1&
#5700000
0&
#5710000
b11111 >
1&
#5720000
0&
#5730000
b100000 >
1&
#5740000
0&
#5750000
b100001 >
1&
#5760000
0&
#5770000
b100010 >
1&
#5780000
0&
#5790000
b100011 >
1&
#5800000
0&
#5810000
b100100 >
1&
#5820000
0&
#5830000
b100101 >
1&
#5840000
0&
#5850000
b100110 >
1&
#5860000
0&
#5870000
b100111 >
1&
#5880000
0&
#5890000
b101000 >
1&
#5900000
0&
#5910000
b101001 >
1&
#5920000
0&
#5930000
b101010 >
1&
#5940000
0&
#5950000
b101011 >
1&
#5960000
0&
#5970000
b101100 >
1&
#5980000
0&
#5990000
b101101 >
1&
#6000000
0&
#6010000
b101110 >
1&
#6020000
0&
#6030000
b101111 >
1&
#6040000
0&
#6050000
b110000 >
1&
#6060000
0&
#6070000
b110001 >
1&
#6080000
0&
#6090000
b110010 >
1&
#6100000
0&
#6110000
b110011 >
1&
#6120000
0&
#6130000
b110100 >
1&
#6140000
0&
#6150000
b110101 >
1&
#6160000
0&
#6170000
b110110 >
1&
