UART/Baud_Generator.v
module baud_tick #(parameter CLK_FREQ =50_000_000,parameter BAUD_RATE=9600)(
input clk,
input reset,
output reg tick_16x
);

localparam DIVISOR = CLK_FREQ/(BAUD_RATE*16);

reg [$clog2(DIVISOR)-1:0] count;

always @(posedge clk) begin
if(reset) begin
count<=0;
tick_16x<=0;
end
else if(count==DIVISOR-1) begin
count<=0;
tick_16x<=1;
end
else begin
count<=count+1;
tick_16x<=0;
end
end
endmodule

UART/baud_tb.v
module baud_tb();
reg clk;
reg reset;
wire tick_16x;

baud_tick dut(clk,reset,tick_16x);

always #10 clk=~clk;
initial begin
	$dumpfile("baud_tick.vcd");
    $dumpvars(0, baud_tb);
clk=0;
reset=1;
#20;
reset=0;
#20000;
$finish;
end
always @(posedge tick_16x) begin
    $display("tick_16x pulsed at time = %0t", $time);
end
endmodule

UART/baud_tick.vcd
$date
	Sat Sep  5 06:29:54 2026
$end
$version
	Icarus Verilog
$end
$timescale
	1s
$end
$scope module baud_tb $end
$var wire 1 ! tick_16x $end
$var reg 1 " clk $end
$var reg 1 # reset $end
$scope module dut $end
$var wire 1 " clk $end
$var wire 1 # reset $end
$var parameter 32 $ BAUD_RATE $end
$var parameter 32 % CLK_FREQ $end
$var parameter 64 & DIVISOR $end
$var reg 9 ' count [8:0] $end
$var reg 1 ! tick_16x $end
$upscope $end
$upscope $end
$enddefinitions $end
$comment Show the parameter values. $end
$dumpall
b101000101 &
b10111110101111000010000000 %
b10010110000000 $
$end
#0
$dumpvars
bx '
1#
0"
x!
$end
#10
0!
b0 '
1"
#20
0"
0#
#30
b1 '
1"
#40
0"
#50
b10 '
1"
#60
0"
#70
b11 '
1"
#80
0"
#90
b100 '
1"
#100
0"
#110
b101 '
1"
#120
0"
#130
b110 '
1"
#140
0"
#150
b111 '
1"
#160
0"
#170
b1000 '
1"
#180
0"
#190
b1001 '
1"
#200
0"
#210
b1010 '
1"
#220
0"
#230
b1011 '
1"
#240
0"
#250
b1100 '
1"
#260
0"
#270
b1101 '
1"
#280
0"
#290
b1110 '
1"
#300
0"
#310
b1111 '
1"
#320
0"
#330
b10000 '
1"
#340
0"
#350
b10001 '
1"
#360
0"
#370
b10010 '
1"
#380
0"
#390
b10011 '
1"
#400
0"
#410
b10100 '
1"
#420
0"
#430
b10101 '
1"
#440
0"
#450
b10110 '
1"
#460
0"
#470
b10111 '
1"
#480
0"
#490
b11000 '
1"
#500
0"
#510
b11001 '
1"
#520
0"
#530
b11010 '
1"
#540
0"
#550
b11011 '
1"
#560
0"
#570
b11100 '
1"
#580
0"
#590
b11101 '
1"
#600
0"
#610
b11110 '
1"
#620
0"
#630
b11111 '
1"
#640
0"
#650
b100000 '
1"
#660
0"
#670
b100001 '
1"
#680
0"
#690
b100010 '
1"
#700
0"
#710
b100011 '
1"
#720
0"
#730
b100100 '
1"
#740
0"
#750
b100101 '
1"
#760
0"
#770
b100110 '
1"
#780
0"
#790
b100111 '
1"
#800
0"
#810
b101000 '
1"
#820
0"
#830
b101001 '
1"
#840
0"
#850
b101010 '
1"
#860
0"
#870
b101011 '
1"
#880
0"
#890
b101100 '
1"
#900
0"
#910
b101101 '
1"
#920
0"
#930
b101110 '
1"
#940
0"
#950
b101111 '
1"
#960
0"
#970
b110000 '
1"
#980
0"
#990
b110001 '
1"
#1000
0"
#1010
b110010 '
1"
#1020
0"
#1030
b110011 '
1"
#1040
0"
#1050
b110100 '
1"
#1060
0"
#1070
b110101 '
1"
#1080
0"
#1090
b110110 '
1"
#1100
0"
#1110
b110111 '
1"
#1120
0"
#1130
b111000 '
1"
#1140
0"
#1150
b111001 '
1"
#1160
0"
#1170
b111010 '
1"
#1180
0"
#1190
b111011 '
1"
#1200
0"
#1210
b111100 '
1"
#1220
0"
#1230
b111101 '
1"
#1240
0"
#1250
b111110 '
1"
#1260
0"
#1270
b111111 '
1"
#1280
0"
#1290
b1000000 '
1"
#1300
0"
#1310
b1000001 '
1"
#1320
0"
#1330
b1000010 '
1"
#1340
0"
#1350
b1000011 '
1"
#1360
0"
#1370
b1000100 '
1"
#1380
0"
#1390
b1000101 '
1"
#1400
0"
#1410
b1000110 '
1"
#1420
0"
#1430
b1000111 '
1"
#1440
0"
#1450
b1001000 '
1"
#1460
0"
#1470
b1001001 '
1"
#1480
0"
#1490
b1001010 '
1"
#1500
0"
#1510
b1001011 '
1"
#1520
0"
#1530
b1001100 '
1"
#1540
0"
#1550
b1001101 '
1"
#1560
0"
#1570
b1001110 '
1"
#1580
0"
#1590
b1001111 '
1"
#1600
0"
#1610
b1010000 '
1"
#1620
0"
#1630
b1010001 '
1"
#1640
0"
#1650
b1010010 '
1"
#1660
0"
#1670
b1010011 '
1"
#1680
0"
#1690
b1010100 '
1"
#1700
0"
#1710
b1010101 '
1"
#1720
0"
#1730
b1010110 '
1"
#1740
0"
#1750
b1010111 '
1"
#1760
0"
#1770
b1011000 '
1"
#1780
0"
#1790
b1011001 '
1"
#1800
0"
#1810
b1011010 '
1"
#1820
0"
#1830
b1011011 '
1"
#1840
0"
#1850
b1011100 '
1"
#1860
0"
#1870
b1011101 '
1"
#1880
0"
#1890
b1011110 '
1"
#1900
0"
#1910
b1011111 '
1"
#1920
0"
#1930
b1100000 '
1"
#1940
0"
#1950
b1100001 '
1"
#1960
0"
#1970
b1100010 '
1"
#1980
0"
#1990
b1100011 '
1"
#2000
0"
#2010
b1100100 '
1"
#2020
0"
#2030
b1100101 '
1"
#2040
0"
#2050
b1100110 '
1"
#2060
0"
#2070
b1100111 '
1"
#2080
0"
#2090
b1101000 '
1"
#2100
0"
#2110
b1101001 '
1"
#2120
0"
#2130
b1101010 '
1"
#2140
0"
#2150
b1101011 '
1"
#2160
0"
#2170
b1101100 '
1"
#2180
0"
#2190
b1101101 '
1"
#2200
0"
#2210
b1101110 '
1"
#2220
0"
#2230
b1101111 '
1"
#2240
0"
#2250
b1110000 '
1"
#2260
0"
#2270
b1110001 '
1"
#2280
0"
#2290
b1110010 '
1"
#2300
0"
#2310
b1110011 '
1"
#2320
0"
#2330
b1110100 '
1"
#2340
0"
#2350
b1110101 '
1"
#2360
0"
#2370
b1110110 '
1"
#2380
0"
#2390
b1110111 '
1"
#2400
0"
#2410
b1111000 '
1"
#2420
0"
#2430
b1111001 '
1"
#2440
0"
#2450
b1111010 '
1"
#2460
0"
#2470
b1111011 '
1"
#2480
0"
#2490
b1111100 '
1"
#2500
0"
#2510
b1111101 '
1"
#2520
0"
#2530
b1111110 '
1"
#2540
0"
#2550
b1111111 '
1"
#2560
0"
#2570
b10000000 '
1"
#2580
0"
#2590
b10000001 '
1"
#2600
0"
#2610
b10000010 '
1"
#2620
0"
#2630
b10000011 '
1"
#2640
0"
#2650
b10000100 '
1"
#2660
0"
#2670
b10000101 '
1"
#2680
0"
#2690
b10000110 '
1"
#2700
0"
#2710
b10000111 '
1"
#2720
0"
#2730
b10001000 '
1"
#2740
0"
#2750
b10001001 '
1"
#2760
0"
#2770
b10001010 '
1"
#2780
0"
#2790
b10001011 '
1"
#2800
0"
#2810
b10001100 '
1"
#2820
0"
#2830
b10001101 '
1"
#2840
0"
#2850
b10001110 '
1"
#2860
0"
#2870
b10001111 '
1"
#2880
0"
#2890
b10010000 '
1"
#2900
0"
#2910
b10010001 '
1"
#2920
0"
#2930
b10010010 '
1"
#2940
0"
#2950
b10010011 '
1"
#2960
0"
#2970
b10010100 '
1"
#2980
0"
#2990
b10010101 '
1"
#3000
0"
#3010
b10010110 '
1"
#3020
0"
#3030
b10010111 '
1"
#3040
0"
#3050
b10011000 '
1"
#3060
0"
#3070
b10011001 '
1"
#3080
0"
#3090
b10011010 '
1"
#3100
0"
#3110
b10011011 '
1"
#3120
0"
#3130
b10011100 '
1"
#3140
0"
#3150
b10011101 '
1"
#3160
0"
#3170
b10011110 '
1"
#3180
0"
#3190
b10011111 '
1"
#3200
0"
#3210
b10100000 '
1"
#3220
0"
#3230
b10100001 '
1"
#3240
0"
#3250
b10100010 '
1"
#3260
0"
#3270
b10100011 '
1"
#3280
0"
#3290
b10100100 '
1"
#3300
0"
#3310
b10100101 '
1"
#3320
0"
#3330
b10100110 '
1"
#3340
0"
#3350
b10100111 '
1"
#3360
0"
#3370
b10101000 '
1"
#3380
0"
#3390
b10101001 '
1"
#3400
0"
#3410
b10101010 '
1"
#3420
0"
#3430
b10101011 '
1"
#3440
0"
#3450
b10101100 '
1"
#3460
0"
#3470
b10101101 '
1"
#3480
0"
#3490
b10101110 '
1"
#3500
0"
#3510
b10101111 '
1"
#3520
0"
#3530
b10110000 '
1"
#3540
0"
#3550
b10110001 '
1"
#3560
0"
#3570
b10110010 '
1"
#3580
0"
#3590
b10110011 '
1"
#3600
0"
#3610
b10110100 '
1"
#3620
0"
#3630
b10110101 '
1"
#3640
0"
#3650
b10110110 '
1"
#3660
0"
#3670
b10110111 '
1"
#3680
0"
#3690
b10111000 '
1"
#3700
0"
#3710
b10111001 '
1"
#3720
0"
#3730
b10111010 '
1"
#3740
0"
#3750
b10111011 '
1"
#3760
0"
#3770
b10111100 '
1"
#3780
0"
#3790
b10111101 '
1"
#3800
0"
#3810
b10111110 '
1"
#3820
0"
#3830
b10111111 '
1"
#3840
0"
#3850
b11000000 '
1"
#3860
0"
#3870
b11000001 '
1"
#3880
0"
#3890
b11000010 '
1"
#3900
0"
#3910
b11000011 '
1"
#3920
0"
#3930
b11000100 '
1"
#3940
0"
#3950
b11000101 '
1"
#3960
0"
#3970
b11000110 '
1"
#3980
0"
#3990
b11000111 '
1"
#4000
0"
#4010
b11001000 '
1"
#4020
0"
#4030
b11001001 '
1"
#4040
0"
#4050
b11001010 '
1"
#4060
0"
#4070
b11001011 '
1"
#4080
0"
#4090
b11001100 '
1"
#4100
0"
#4110
b11001101 '
1"
#4120
0"
#4130
b11001110 '
1"
#4140
0"
#4150
b11001111 '
1"
#4160
0"
#4170
b11010000 '
1"
#4180
0"
#4190
b11010001 '
1"
#4200
0"
#4210
b11010010 '
1"
#4220
0"
#4230
b11010011 '
1"
#4240
0"
#4250
b11010100 '
1"
#4260
0"
#4270
b11010101 '
1"
#4280
0"
#4290
b11010110 '
1"
#4300
0"
#4310
b11010111 '
1"
#4320
0"
#4330
b11011000 '
1"
#4340
0"
#4350
b11011001 '
1"
#4360
0"
#4370
b11011010 '
1"
#4380
0"
#4390
b11011011 '
1"
#4400
0"
#4410
b11011100 '
1"
#4420
0"
#4430
b11011101 '
1"
#4440
0"
#4450
b11011110 '
1"
#4460
0"
#4470
b11011111 '
1"
#4480
0"
#4490
b11100000 '
1"
#4500
0"
#4510
b11100001 '
1"
#4520
0"
#4530
b11100010 '
1"
#4540
0"
#4550
b11100011 '
1"
#4560
0"
#4570
b11100100 '
1"
#4580
0"
#4590
b11100101 '
1"
#4600
0"
#4610
b11100110 '
1"
#4620
0"
#4630
b11100111 '
1"
#4640
0"
#4650
b11101000 '
1"
#4660
0"
#4670
b11101001 '
1"
#4680
0"
#4690
b11101010 '
1"
#4700
0"
#4710
b11101011 '
1"
#4720
0"
#4730
b11101100 '
1"
#4740
0"
#4750
b11101101 '
1"
#4760
0"
#4770
b11101110 '
1"
#4780
0"
#4790
b11101111 '
1"
#4800
0"
#4810
b11110000 '
1"
#4820
0"
#4830
b11110001 '
1"
#4840
0"
#4850
b11110010 '
1"
#4860
0"
#4870
b11110011 '
1"
#4880
0"
#4890
b11110100 '
1"
#4900
0"
#4910
b11110101 '
1"
#4920
0"
#4930
b11110110 '
1"
#4940
0"
#4950
b11110111 '
1"
#4960
0"
#4970
b11111000 '
1"
#4980
0"
#4990
b11111001 '
1"
#5000
0"
#5010
b11111010 '
1"
#5020
0"
#5030
b11111011 '
1"
#5040
0"
#5050
b11111100 '
1"
#5060
0"
#5070
b11111101 '
1"
#5080
0"
#5090
b11111110 '
1"
#5100
0"
#5110
b11111111 '
1"
#5120
0"
#5130
b100000000 '
1"
#5140
0"
#5150
b100000001 '
1"
#5160
0"
#5170
b100000010 '
1"
#5180
0"
#5190
b100000011 '
1"
#5200
0"
#5210
b100000100 '
1"
#5220
0"
#5230
b100000101 '
1"
#5240
0"
#5250
b100000110 '
1"
#5260
0"
#5270
b100000111 '
1"
#5280
0"
#5290
b100001000 '
1"
#5300
0"
#5310
b100001001 '
1"
#5320
0"
#5330
b100001010 '
1"
#5340
0"
#5350
b100001011 '
1"
#5360
0"
#5370
b100001100 '
1"
#5380
0"
#5390
b100001101 '
1"
#5400
0"
#5410
b100001110 '
1"
#5420
0"
#5430
b100001111 '
1"
#5440
0"
#5450
b100010000 '
1"
#5460
0"
#5470
b100010001 '
1"
#5480
0"
#5490
b100010010 '
1"
#5500
0"
#5510
b100010011 '
1"
#5520
0"
#5530
b100010100 '
1"
#5540
0"
#5550
b100010101 '
1"
#5560
0"
#5570
b100010110 '
1"
#5580
0"
#5590
b100010111 '
1"
#5600
0"
#5610
b100011000 '
1"
#5620
0"
#5630
b100011001 '
1"
#5640
0"
#5650
b100011010 '
1"
#5660
0"
#5670
b100011011 '
1"
#5680
0"
#5690
b100011100 '
1"
#5700
0"
#5710
b100011101 '
1"
#5720
0"
#5730
b100011110 '
1"
#5740
0"
#5750
b100011111 '
1"
#5760
0"
#5770
b100100000 '
1"
#5780
0"
#5790
b100100001 '
1"
#5800
0"
#5810
b100100010 '
1"
#5820
0"
#5830
b100100011 '
1"
#5840
0"
#5850
b100100100 '
1"
#5860
0"
#5870
b100100101 '
1"
#5880
0"
#5890
b100100110 '
1"
#5900
0"
#5910
b100100111 '
1"
#5920
0"
#5930
b100101000 '
1"
#5940
0"
#5950
b100101001 '
1"
#5960
0"
#5970
b100101010 '
1"
#5980
0"
#5990
b100101011 '
1"
#6000
0"
#6010
b100101100 '
1"
#6020
0"
#6030
b100101101 '
1"
#6040
0"
#6050
b100101110 '
1"
#6060
0"
#6070
b100101111 '
1"
#6080
0"
#6090
b100110000 '
1"
#6100
0"
#6110
b100110001 '
1"
#6120
0"
#6130
b100110010 '
1"
#6140
0"
#6150
b100110011 '
1"
#6160
0"
#6170
b100110100 '
1"
#6180
0"
#6190
b100110101 '
1"
#6200
0"
#6210
b100110110 '
1"
#6220
0"
#6230
b100110111 '
1"
#6240
0"
#6250
b100111000 '
1"
#6260
0"
#6270
b100111001 '
1"
#6280
0"
#6290
b100111010 '
1"
#6300
0"
#6310
b100111011 '
1"
#6320
0"
#6330
b100111100 '
1"
#6340
0"
#6350
b100111101 '
1"
#6360
0"
#6370
b100111110 '
1"
#6380
0"
#6390
b100111111 '
1"
#6400
0"
#6410
b101000000 '
1"
#6420
0"
#6430
b101000001 '
1"
#6440
0"
#6450
b101000010 '
1"
#6460
0"
#6470
b101000011 '
1"
#6480
0"
#6490
b101000100 '
1"
#6500
0"
#6510
1!
b0 '
1"
#6520
0"
#6530
0!
b1 '
1"
#6540
0"
#6550
b10 '
1"
#6560
0"
#6570
b11 '
1"
#6580
0"
#6590
b100 '
1"
#6600
0"
#6610
b101 '
1"
#6620
0"
#6630
b110 '
1"
#6640
0"
#6650
b111 '
1"
#6660
0"
#6670
b1000 '
1"
#6680
0"
#6690
b1001 '
1"
#6700
0"
#6710
b1010 '
1"
#6720
0"
#6730
b1011 '
1"
#6740
0"
#6750
b1100 '
1"
#6760
0"
#6770
b1101 '
1"
#6780
0"
#6790
b1110 '
1"
#6800
0"
#6810
b1111 '
1"
#6820
0"
#6830
b10000 '
1"
#6840
0"
#6850
b10001 '
1"
#6860
0"
#6870
b10010 '
1"
#6880
0"
#6890
b10011 '
1"
#6900
0"
#6910
b10100 '
1"
#6920
0"
#6930
b10101 '
1"
#6940
0"
#6950
b10110 '
1"
#6960
0"
#6970
b10111 '
1"
#6980
0"
#6990
b11000 '
1"
#7000
0"
#7010
b11001 '
1"
#7020
0"
#7030
b11010 '
1"
#7040
0"
#7050
b11011 '
1"
#7060
0"
#7070
b11100 '
1"
#7080
0"
#7090
b11101 '
1"
#7100
0"
#7110
b11110 '
1"
#7120
0"
#7130
b11111 '
1"
#7140
0"
#7150
b100000 '
1"
#7160
0"
#7170
b100001 '
1"
#7180
0"
#7190
b100010 '
1"
#7200
0"
#7210
b100011 '
1"
#7220
0"
#7230
b100100 '
1"
#7240
0"
#7250
b100101 '
1"
#7260
0"
#7270
b100110 '
1"
#7280
0"
#7290
b100111 '
1"
#7300
0"
#7310
b101000 '
1"
#7320
0"
#7330
b101001 '
1"
#7340
0"
#7350
b101010 '
1"
#7360
0"
#7370
b101011 '
1"
#7380
0"
#7390
b101100 '
1"
#7400
0"
#7410
b101101 '
1"
#7420
0"
#7430
b101110 '
1"
#7440
0"
#7450
b101111 '
1"
#7460
0"
#7470
b110000 '
1"
#7480
0"
#7490
b110001 '
1"
#7500
0"
#7510
b110010 '
1"
#7520
0"
#7530
b110011 '
1"
#7540
0"
#7550
b110100 '
1"
#7560
0"
#7570
b110101 '
1"
#7580
0"
#7590
b110110 '
1"
#7600
0"
#7610
b110111 '
1"
#7620
0"
#7630
b111000 '
1"
#7640
0"
#7650
b111001 '
1"
#7660
0"
#7670
b111010 '
1"
#7680
0"
#7690
b111011 '
1"
#7700
0"
#7710
b111100 '
1"
#7720
0"
#7730
b111101 '
1"
#7740
0"
#7750
b111110 '
1"
#7760
0"
#7770
b111111 '
1"
#7780
0"
#7790
b1000000 '
1"
#7800
0"
#7810
b1000001 '
1"
#7820
0"
#7830
b1000010 '
1"
#7840
0"
#7850
b1000011 '
1"
#7860
0"
#7870
b1000100 '
1"
#7880
0"
#7890
b1000101 '
1"
#7900
0"
#7910
b1000110 '
1"
#7920
0"
#7930
b1000111 '
1"
#7940
0"
#7950
b1001000 '
1"
#7960
0"
#7970
b1001001 '
1"
#7980
0"
#7990
b1001010 '
1"
#8000
0"
#8010
b1001011 '
1"
#8020
0"
#8030
b1001100 '
1"
#8040
0"
#8050
b1001101 '
1"
#8060
0"
#8070
b1001110 '
1"
#8080
0"
#8090
b1001111 '
1"
#8100
0"
#8110
b1010000 '
1"
#8120
0"
#8130
b1010001 '
1"
#8140
0"
#8150
b1010010 '
1"
#8160
0"
#8170
b1010011 '
1"
#8180
0"
#8190
b1010100 '
1"
#8200
0"
#8210
b1010101 '
1"
#8220
0"
#8230
b1010110 '
1"
#8240
0"
#8250
b1010111 '
1"
#8260
0"
#8270
b1011000 '
1"
#8280
0"
#8290
b1011001 '
1"
#8300
0"
#8310
b1011010 '
1"
#8320
0"
#8330
b1011011 '
1"
#8340
0"
#8350
b1011100 '
1"
#8360
0"
#8370
b1011101 '
1"
#8380
0"
#8390
b1011110 '
1"
#8400
0"
#8410
b1011111 '
1"
#8420
0"
#8430
b1100000 '
1"
#8440
0"
#8450
b1100001 '
1"
#8460
0"
#8470
b1100010 '
1"
#8480
0"
#8490
b1100011 '
1"
#8500
0"
#8510
b1100100 '
1"
#8520
0"
#8530
b1100101 '
1"
#8540
0"
#8550
b1100110 '
1"
#8560
0"
#8570
b1100111 '
1"
#8580
0"
#8590
b1101000 '
1"
#8600
0"
#8610
b1101001 '
1"
#8620
0"
#8630
b1101010 '
1"
#8640
0"
#8650
b1101011 '
1"
#8660
0"
#8670
b1101100 '
1"
#8680
0"
#8690
b1101101 '
1"
#8700
0"
#8710
b1101110 '
1"
#8720
0"
#8730
b1101111 '
1"
#8740
0"
#8750
b1110000 '
1"
#8760
0"
#8770
b1110001 '
1"
#8780
0"
#8790
b1110010 '
1"
#8800
0"
#8810
b1110011 '
1"
#8820
0"
#8830
b1110100 '
1"
#8840
0"
#8850
b1110101 '
1"
#8860
0"
#8870
b1110110 '
1"
#8880
0"
#8890
b1110111 '
1"
#8900
0"
#8910
b1111000 '
1"
#8920
0"
#8930
b1111001 '
1"
#8940
0"
#8950
b1111010 '
1"
#8960
0"
#8970
b1111011 '
1"
#8980
0"
#8990
b1111100 '
1"
#9000
0"
#9010
b1111101 '
1"
#9020
0"
#9030
b1111110 '
1"
#9040
0"
#9050
b1111111 '
1"
#9060
0"
#9070
b10000000 '
1"
#9080
0"
#9090
b10000001 '
1"
#9100
0"
#9110
b10000010 '
1"
#9120
0"
#9130
b10000011 '
1"
#9140
0"
#9150
b10000100 '
1"
#9160
0"
#9170
b10000101 '
1"
#9180
0"
#9190
b10000110 '
1"
#9200
0"
#9210
b10000111 '
1"
#9220
0"
#9230
b10001000 '
1"
#9240
0"
#9250
b10001001 '
1"
#9260
0"
#9270
b10001010 '
1"
#9280
0"
#9290
b10001011 '
1"
#9300
0"
#9310
b10001100 '
1"
#9320
0"
#9330
b10001101 '
1"
#9340
0"
#9350
b10001110 '
1"
#9360
0"
#9370
b10001111 '
1"
#9380
0"
#9390
b10010000 '
1"
#9400
0"
#9410
b10010001 '
1"
#9420
0"
#9430
b10010010 '
1"
#9440
0"
#9450
b10010011 '
1"
#9460
0"
#9470
b10010100 '
1"
#9480
0"
#9490
b10010101 '
1"
#9500
0"
#9510
b10010110 '
1"
#9520
0"
#9530
b10010111 '
1"
#9540
0"
#9550
b10011000 '
1"
#9560
0"
#9570
b10011001 '
1"
#9580
0"
#9590
b10011010 '
1"
#9600
0"
#9610
b10011011 '
1"
#9620
0"
#9630
b10011100 '
1"
#9640
0"
#9650
b10011101 '
1"
#9660
0"
#9670
b10011110 '
1"
#9680
0"
#9690
b10011111 '
1"
#9700
0"
#9710
b10100000 '
1"
#9720
0"
#9730
b10100001 '
1"
#9740
0"
#9750
b10100010 '
1"
#9760
0"
#9770
b10100011 '
1"
#9780
0"
#9790
b10100100 '
1"
#9800
0"
#9810
b10100101 '
1"
#9820
0"
#9830
b10100110 '
1"
#9840
0"
#9850
b10100111 '
1"
#9860
0"
#9870
b10101000 '
1"
#9880
0"
#9890
b10101001 '
1"
#9900
0"
#9910
b10101010 '
1"
#9920
0"
#9930
b10101011 '
1"
#9940
0"
#9950
b10101100 '
1"
#9960
0"
#9970
b10101101 '
1"
#9980
0"
#9990
b10101110 '
1"
#10000
0"
#10010
b10101111 '
1"
#10020
0"
#10030
b10110000 '
1"
#10040
0"
#10050
b10110001 '
1"
#10060
0"
#10070
b10110010 '
1"
#10080
0"
#10090
b10110011 '
1"
#10100
0"
#10110
b10110100 '
1"
#10120
0"
#10130
b10110101 '
1"
#10140
0"
#10150
b10110110 '
1"
#10160
0"
#10170
b10110111 '
1"
#10180
0"
#10190
b10111000 '
1"
#10200
0"
#10210
b10111001 '
1"
#10220
0"
#10230
b10111010 '
1"
#10240
0"
#10250
b10111011 '
1"
#10260
0"
#10270
b10111100 '
1"
#10280
0"
#10290
b10111101 '
1"
#10300
0"
#10310
b10111110 '
1"
#10320
0"
#10330
b10111111 '
1"
#10340
0"
#10350
b11000000 '
1"
#10360
0"
#10370
b11000001 '
1"
#10380
0"
#10390
b11000010 '
1"
#10400
0"
#10410
b11000011 '
1"
#10420
0"
#10430
b11000100 '
1"
#10440
0"
#10450
b11000101 '
1"
#10460
0"
#10470
b11000110 '
1"
#10480
0"
#10490
b11000111 '
1"
#10500
0"
#10510
b11001000 '
1"
#10520
0"
#10530
b11001001 '
1"
#10540
0"
#10550
b11001010 '
1"
#10560
0"
#10570
b11001011 '
1"
#10580
0"
#10590
b11001100 '
1"
#10600
0"
#10610
b11001101 '
1"
#10620
0"
#10630
b11001110 '
1"
#10640
0"
#10650
b11001111 '
1"
#10660
0"
#10670
b11010000 '
1"
#10680
0"
#10690
b11010001 '
1"
#10700
0"
#10710
b11010010 '
1"
#10720
0"
#10730
b11010011 '
1"
#10740
0"
#10750
b11010100 '
1"
#10760
0"
#10770
b11010101 '
1"
#10780
0"
#10790
b11010110 '
1"
#10800
0"
#10810
b11010111 '
1"
#10820
0"
#10830
b11011000 '
1"
#10840
0"
#10850
b11011001 '
1"
#10860
0"
#10870
b11011010 '
1"
#10880
0"
#10890
b11011011 '
1"
#10900
0"
#10910
b11011100 '
1"
#10920
0"
#10930
b11011101 '
1"
#10940
0"
#10950
b11011110 '
1"
#10960
0"
#10970
b11011111 '
1"
#10980
0"
#10990
b11100000 '
1"
#11000
0"
#11010
b11100001 '
1"
#11020
0"
#11030
b11100010 '
1"
#11040
0"
#11050
b11100011 '
1"
#11060
0"
#11070
b11100100 '
1"
#11080
0"
#11090
b11100101 '
1"
#11100
0"
#11110
b11100110 '
1"
#11120
0"
#11130
b11100111 '
1"
#11140
0"
#11150
b11101000 '
1"
#11160
0"
#11170
b11101001 '
1"
#11180
0"
#11190
b11101010 '
1"
#11200
0"
#11210
b11101011 '
1"
#11220
0"
#11230
b11101100 '
1"
#11240
0"
#11250
b11101101 '
1"
#11260
0"
#11270
b11101110 '
1"
#11280
0"
#11290
b11101111 '
1"
#11300
0"
#11310
b11110000 '
1"
#11320
0"
#11330
b11110001 '
1"
#11340
0"
#11350
b11110010 '
1"
#11360
0"
#11370
b11110011 '
1"
#11380
0"
#11390
b11110100 '
1"
#11400
0"
#11410
b11110101 '
1"
#11420
0"
#11430
b11110110 '
1"
#11440
0"
#11450
b11110111 '
1"
#11460
0"
#11470
b11111000 '
1"
#11480
0"
#11490
b11111001 '
1"
#11500
0"
#11510
b11111010 '
1"
#11520
0"
#11530
b11111011 '
1"
#11540
0"
#11550
b11111100 '
1"
#11560
0"
#11570
b11111101 '
1"
#11580
0"
#11590
b11111110 '
1"
#11600
0"
#11610
b11111111 '
1"
#11620
0"
#11630
b100000000 '
1"
#11640
0"
#11650
b100000001 '
1"
#11660
0"
#11670
b100000010 '
1"
#11680
0"
#11690
b100000011 '
1"
#11700
0"
#11710
b100000100 '
1"
#11720
0"
#11730
b100000101 '
1"
#11740
0"
#11750
b100000110 '
1"
#11760
0"
#11770
b100000111 '
1"
#11780
0"
#11790
b100001000 '
1"
#11800
0"
#11810
b100001001 '
1"
#11820
0"
#11830
b100001010 '
1"
#11840
0"
#11850
b100001011 '
1"
#11860
0"
#11870
b100001100 '
1"
#11880
0"
#11890
b100001101 '
1"
#11900
0"
#11910
b100001110 '
1"
#11920
0"
#11930
b100001111 '
1"
#11940
0"
#11950
b100010000 '
1"
#11960
0"
#11970
b100010001 '
1"
#11980
0"
#11990
b100010010 '
1"
#12000
0"
#12010
b100010011 '
1"
#12020
0"
#12030
b100010100 '
1"
#12040
0"
#12050
b100010101 '
1"
#12060
0"
#12070
b100010110 '
1"
#12080
0"
#12090
b100010111 '
1"
#12100
0"
#12110
b100011000 '
1"
#12120
0"
#12130
b100011001 '
1"
#12140
0"
#12150
b100011010 '
1"
#12160
0"
#12170
b100011011 '
1"
#12180
0"
#12190
b100011100 '
1"
#12200
0"
#12210
b100011101 '
1"
#12220
0"
#12230
b100011110 '
1"
#12240
0"
#12250
b100011111 '
1"
#12260
0"
#12270
b100100000 '
1"
#12280
0"
#12290
b100100001 '
1"
#12300
0"
#12310
b100100010 '
1"
#12320
0"
#12330
b100100011 '
1"
#12340
0"
#12350
b100100100 '
1"
#12360
0"
#12370
b100100101 '
1"
#12380
0"
#12390
b100100110 '
1"
#12400
0"
#12410
b100100111 '
1"
#12420
0"
#12430
b100101000 '
1"
#12440
0"
#12450
b100101001 '
1"
#12460
0"
#12470
b100101010 '
1"
#12480
0"
#12490
b100101011 '
1"
#12500
0"
#12510
b100101100 '
1"
#12520
0"
#12530
b100101101 '
1"
#12540
0"
#12550
b100101110 '
1"
#12560
0"
#12570
b100101111 '
1"
#12580
0"
#12590
b100110000 '
1"
#12600
0"
#12610
b100110001 '
1"
#12620
0"
#12630
b100110010 '
1"
#12640
0"
#12650
b100110011 '
1"
#12660
0"
#12670
b100110100 '
1"
#12680
0"
#12690
b100110101 '
1"
#12700
0"
#12710
b100110110 '
1"
#12720
0"
#12730
b100110111 '
1"
#12740
0"
#12750
b100111000 '
1"
#12760
0"
#12770
b100111001 '
1"
#12780
0"
#12790
b100111010 '
1"
#12800
0"
#12810
b100111011 '
1"
#12820
0"
#12830
b100111100 '
1"
#12840
0"
#12850
b100111101 '
1"
#12860
0"
#12870
b100111110 '
1"
#12880
0"
#12890
b100111111 '
1"
#12900
0"
#12910
b101000000 '
1"
#12920
0"
#12930
b101000001 '
1"
#12940
0"
#12950
b101000010 '
1"
#12960
0"
#12970
b101000011 '
1"
#12980
0"
#12990
b101000100 '
1"
#13000
0"
#13010
1!
b0 '
1"
#13020
0"
#13030
0!
b1 '
1"
#13040
0"
#13050
b10 '
1"
#13060
0"
#13070
b11 '
1"
#13080
0"
#13090
b100 '
1"
#13100
0"
#13110
b101 '
1"
#13120
0"
#13130
b110 '
1"
#13140
0"
#13150
b111 '
1"
#13160
0"
#13170
b1000 '
1"
#13180
0"
#13190
b1001 '
1"
#13200
0"
#13210
b1010 '
1"
#13220
0"
#13230
b1011 '
1"
#13240
0"
#13250
b1100 '
1"
#13260
0"
#13270
b1101 '
1"
#13280
0"
#13290
b1110 '
1"
#13300
0"
#13310
b1111 '
1"
#13320
0"
#13330
b10000 '
1"
#13340
0"
#13350
b10001 '
1"
#13360
0"
#13370
b10010 '
1"
#13380
0"
#13390
b10011 '
1"
#13400
0"
#13410
b10100 '
1"
#13420
0"
#13430
b10101 '
1"
#13440
0"
#13450
b10110 '
1"
#13460
0"
#13470
b10111 '
1"
#13480
0"
#13490
b11000 '
1"
#13500
0"
#13510
b11001 '
1"
#13520
0"
#13530
b11010 '
1"
#13540
0"
#13550
b11011 '
1"
#13560
0"
#13570
b11100 '
1"
#13580
0"
#13590
b11101 '
1"
#13600
0"
#13610
b11110 '
1"
#13620
0"
#13630
b11111 '
1"
#13640
0"
#13650
b100000 '
1"
#13660
0"
#13670
b100001 '
1"
#13680
0"
#13690
b100010 '
1"
#13700
0"
#13710
b100011 '
1"
#13720
0"
#13730
b100100 '
1"
#13740
0"
#13750
b100101 '
1"
#13760
0"
#13770
b100110 '
1"
#13780
0"
#13790
b100111 '
1"
#13800
0"
