SPI/spi.v
module spi(
input clk,rst,start,miso,
input [3:0] data_in,
output reg sclk,cs,mosi,
output reg [3:0] data_out,
output reg busy,done
);
localparam idle=2'b00,load=2'b01,shift=2'b10,finish=2'b11;
reg [1:0] state, next_state;
reg [3:0] bit_cnt;
reg [3:0] tx_reg;
reg [3:0] rx_reg;
always @(posedge clk) begin
if(rst)
state<=idle;
else 
state<=next_state;
end 



always @(*) begin
case(state) 
idle: begin
if(start) 
next_state=load;
else
next_state=idle;
end
load: begin
next_state=shift;
end
shift: begin
if(bit_cnt==0)
next_state=finish;
else
next_state=shift;
end
finish: begin
next_state=idle;
end
endcase
end

always @(posedge clk) begin
	if(rst) begin
		tx_reg<=4'b0;
		rx_reg<=4'b0;
		bit_cnt<=4'b0;
		data_out<=4'b0;
		sclk<=1'b0;
		cs<=1'b1;
		mosi<=1'b0;
		busy<=1'b0;
		done<=1'b0;
	end
	else begin 
		done<=1'b0;
		case(state)
			idle: begin
				cs<=1'b0;
				sclk<=1'b0;
				busy<=1'b1;
			end
			load: begin
                tx_reg  <= data_in;
                rx_reg  <= 4'b0;
                bit_cnt <= 4'd3;
                cs      <= 1'b0;
                busy    <= 1'b1;
                mosi    <= data_in[3];
            end
	    shift: begin
                sclk <= ~sclk;

                if(sclk == 1'b0) begin
                    rx_reg[bit_cnt] <= miso;
                end
                else begin
                    if(bit_cnt != 0) begin
                        bit_cnt <= bit_cnt - 1'b1;
                        mosi <= tx_reg[bit_cnt-1];
                    end
                end
            end

            finish: begin
                cs       <= 1'b1;
                sclk     <= 1'b0;
                busy     <= 1'b0;
                data_out <= rx_reg;
		done     <= 1'b1;
            end
        endcase
    end
end

endmodule

SPI/spi_tb.v
module spi_tb;

reg clk;
reg rst;
reg start;
reg miso;
reg [3:0] data_in;

wire sclk;
wire cs;
wire mosi;
wire [3:0] data_out;
wire busy;
wire done;

spi dut(
    .clk(clk),
    .rst(rst),
    .start(start),
    .miso(miso),
    .data_in(data_in),
    .sclk(sclk),
    .cs(cs),
    .mosi(mosi),
    .data_out(data_out),
    .busy(busy),
    .done(done)
);

always #5 clk = ~clk;

initial begin
	$dumpfile("spi.vcd");
	$dumpvars(0,spi_tb);
    clk = 0;
    rst = 1;
    start = 0;
    miso = 0;
    data_in = 4'b1010;

    #10;
    rst = 0;

    #10;
    start = 1;

    #10;
    start = 0;

    #20;
    miso = 1;

    #20;
    miso = 0;

    #20;
    miso = 1;

    #20;
    miso = 1;

    #100;
    $finish;
end

initial begin
    $monitor("time=%0t clk=%b rst=%b start=%b cs=%b sclk=%b mosi=%b miso=%b data_out=%b busy=%b done=%b",
             $time,clk,rst,start,cs,sclk,mosi,miso,data_out,busy,done);
end

endmodule

SPI/spi.vcd
$date
	Wed Sep  2 14:09:09 2026
$end
$version
	Icarus Verilog
$end
$timescale
	1s
$end
$scope module spi_tb $end
$var wire 1 ! sclk $end
$var wire 1 " mosi $end
$var wire 1 # done $end
$var wire 4 $ data_out [3:0] $end
$var wire 1 % cs $end
$var wire 1 & busy $end
$var reg 1 ' clk $end
$var reg 4 ( data_in [3:0] $end
$var reg 1 ) miso $end
$var reg 1 * rst $end
$var reg 1 + start $end
$scope module dut $end
$var wire 1 ' clk $end
$var wire 4 , data_in [3:0] $end
$var wire 1 ) miso $end
$var wire 1 * rst $end
$var wire 1 + start $end
$var parameter 2 - finish $end
$var parameter 2 . idle $end
$var parameter 2 / load $end
$var parameter 2 0 shift $end
$var reg 4 1 bit_cnt [3:0] $end
$var reg 1 & busy $end
$var reg 1 % cs $end
$var reg 4 2 data_out [3:0] $end
$var reg 1 # done $end
$var reg 1 " mosi $end
$var reg 2 3 next_state [1:0] $end
$var reg 4 4 rx_reg [3:0] $end
$var reg 1 ! sclk $end
$var reg 2 5 state [1:0] $end
$var reg 4 6 tx_reg [3:0] $end
$upscope $end
$upscope $end
$enddefinitions $end
$comment Show the parameter values. $end
$dumpall
b10 0
b1 /
b0 .
b11 -
$end
#0
$dumpvars
bx 6
bx 5
bx 4
bx 3
bx 2
bx 1
b1010 ,
0+
1*
0)
b1010 (
0'
x&
x%
bx $
x#
x"
x!
$end
#5
b0 3
b0 5
0#
0&
0"
1%
0!
b0 $
b0 2
b0 1
b0 4
b0 6
1'
#10
0'
0*
#15
1&
0%
1'
#20
b1 3
0'
1+
#25
b10 3
b1 5
1'
#30
0'
0+
#35
1"
b11 1
b1010 6
b10 5
1'
#40
0'
#45
1!
1'
#50
0'
1)
#55
0"
b10 1
0!
1'
#60
0'
#65
b100 4
1!
1'
#70
0'
0)
#75
1"
b1 1
0!
1'
#80
0'
#85
1!
1'
#90
0'
1)
#95
b11 3
0"
b0 1
0!
1'
#100
0'
#105
b0 3
b11 5
b101 4
1!
1'
#110
0'
#115
1#
b101 $
b101 2
0&
0!
1%
b0 5
1'
#120
0'
#125
1&
0%
0#
1'
